{
      "1":{
         "properties":{
            "OBJECTID":10858,
            "secRef":"1503001001",
            "CUMUN":"15030",
            "CSEC":"001",
            "CDIS":"01",
            "CMUN":"030",
            "CPRO":"15",
            "CCA":"12",
            "CUDIS":"1503001",
            "Shape_Leng":1796.6169036399999,
            "Shape_area":92594.633282700001,
            "Shape_len":1796.6169036399999
         },
         "geometry":{
            "coordinates":[
               [
                  -8.39591389125016,
                  43.372132843172352
               ],
               [
                  -8.39588278746068,
                  43.372173839375094
               ],
               [
                  -8.395708371684808,
                  43.371994962022832
               ],
               [
                  -8.395469483052846,
                  43.371899057889046
               ],
               [
                  -8.395360442485432,
                  43.371841494097403
               ],
               [
                  -8.395318183094417,
                  43.371819285672153
               ],
               [
                  -8.395071398908778,
                  43.371704430947041
               ],
               [
                  -8.394806652134484,
                  43.371584011400167
               ],
               [
                  -8.394850228868187,
                  43.371255765921596
               ],
               [
                  -8.394900490859188,
                  43.370876462970799
               ],
               [
                  -8.394964458825386,
                  43.37039433423476
               ],
               [
                  -8.394816989485216,
                  43.370302714075727
               ],
               [
                  -8.394625842805176,
                  43.370183712804355
               ],
               [
                  -8.394771906202237,
                  43.370071028004929
               ],
               [
                  -8.394987081078138,
                  43.369919364920321
               ],
               [
                  -8.394706740678881,
                  43.369806794633277
               ],
               [
                  -8.394643654120195,
                  43.369822284235703
               ],
               [
                  -8.394488154094725,
                  43.3697941682235
               ],
               [
                  -8.3944381206706,
                  43.369752157693867
               ],
               [
                  -8.394290496919638,
                  43.369702836701876
               ],
               [
                  -8.394117494791097,
                  43.369706044145467
               ],
               [
                  -8.393904759805009,
                  43.369692121646963
               ],
               [
                  -8.393684647869911,
                  43.369669198847191
               ],
               [
                  -8.393620950432272,
                  43.369684675365406
               ],
               [
                  -8.393680460853874,
                  43.369481841347152
               ],
               [
                  -8.393644670603248,
                  43.369436037473463
               ],
               [
                  -8.393604066318186,
                  43.369384106603746
               ],
               [
                  -8.393578358115789,
                  43.369351288692116
               ],
               [
                  -8.393565344174716,
                  43.369355019023232
               ],
               [
                  -8.393546527037065,
                  43.369360501109114
               ],
               [
                  -8.393483779818597,
                  43.369280390837226
               ],
               [
                  -8.393528253926045,
                  43.369261803242033
               ],
               [
                  -8.393565252957881,
                  43.369242206256231
               ],
               [
                  -8.393315119976762,
                  43.368915521961711
               ],
               [
                  -8.393805285759871,
                  43.36874120677895
               ],
               [
                  -8.393869251144395,
                  43.368646270843527
               ],
               [
                  -8.394516639395215,
                  43.368379428999155
               ],
               [
                  -8.396985045109695,
                  43.36847019307951
               ],
               [
                  -8.396977534254079,
                  43.368570145814999
               ],
               [
                  -8.396431744524641,
                  43.368580622217941
               ],
               [
                  -8.396336990880332,
                  43.368582451601064
               ],
               [
                  -8.396267362991226,
                  43.369603037414365
               ],
               [
                  -8.398475392414079,
                  43.369814498939085
               ],
               [
                  -8.398646685874567,
                  43.369917967615784
               ],
               [
                  -8.398681006810888,
                  43.369980430587653
               ],
               [
                  -8.398875754094808,
                  43.370334985471708
               ],
               [
                  -8.398861156567571,
                  43.370449912390264
               ],
               [
                  -8.399078065928157,
                  43.370422567777027
               ],
               [
                  -8.399064145036018,
                  43.370566941430603
               ],
               [
                  -8.399070257537513,
                  43.370772558543315
               ],
               [
                  -8.399059708531905,
                  43.370791233549411
               ],
               [
                  -8.398709003381041,
                  43.370833506312451
               ],
               [
                  -8.398618284241131,
                  43.370844382911358
               ],
               [
                  -8.398310405924802,
                  43.370862462408361
               ],
               [
                  -8.397666289301545,
                  43.370921297562205
               ],
               [
                  -8.397734358829545,
                  43.371236813408089
               ],
               [
                  -8.397275867469729,
                  43.371229720329318
               ],
               [
                  -8.397005011261211,
                  43.371228142076312
               ],
               [
                  -8.396821077800993,
                  43.371212825898752
               ],
               [
                  -8.39680753090741,
                  43.371211675603028
               ],
               [
                  -8.396729084946914,
                  43.371205158131488
               ],
               [
                  -8.396620572597739,
                  43.371196133168027
               ],
               [
                  -8.396588234908082,
                  43.371193423537513
               ],
               [
                  -8.396559500872893,
                  43.371191133898513
               ],
               [
                  -8.396499424204787,
                  43.37118601458625
               ],
               [
                  -8.396431242317965,
                  43.371180351589665
               ],
               [
                  -8.396411912120916,
                  43.371325039459641
               ],
               [
                  -8.396446360656533,
                  43.371382499929467
               ],
               [
                  -8.39648381425055,
                  43.37142025719254
               ],
               [
                  -8.396526438117551,
                  43.371441983417419
               ],
               [
                  -8.396726489241535,
                  43.371468339206082
               ],
               [
                  -8.396837911125722,
                  43.37148308592316
               ],
               [
                  -8.396832946737701,
                  43.371584962535778
               ],
               [
                  -8.396786537090801,
                  43.371707646881489
               ],
               [
                  -8.396749683831747,
                  43.371743942588871
               ],
               [
                  -8.396723774949443,
                  43.371741369847527
               ],
               [
                  -8.396538196261048,
                  43.371722903778334
               ],
               [
                  -8.396429206746088,
                  43.371732946370486
               ],
               [
                  -8.396308522087519,
                  43.371766979665686
               ],
               [
                  -8.39620539263546,
                  43.37182280111378
               ],
               [
                  -8.396180149584987,
                  43.371845826133885
               ],
               [
                  -8.396146359505234,
                  43.371876260262923
               ],
               [
                  -8.395967361337188,
                  43.372066777779104
               ],
               [
                  -8.395949120523206,
                  43.372086186476722
               ],
               [
                  -8.39591389125016,
                  43.372132843172352
               ]
            ]
         }
      },
      "2":{
         "properties":{
            "OBJECTID":10859,
            "secRef":"1503001002",
            "CUMUN":"15030",
            "CSEC":"002",
            "CDIS":"01",
            "CMUN":"030",
            "CPRO":"15",
            "CCA":"12",
            "CUDIS":"1503001",
            "Shape_Leng":977.67288778,
            "Shape_area":29110.1425829,
            "Shape_len":977.67288778199998
         },
         "geometry":{
            "coordinates":[
               [
                  -8.399258677845971,
                  43.371757267796944
               ],
               [
                  -8.398924237064472,
                  43.371860351887662
               ],
               [
                  -8.398249997673039,
                  43.372068143612751
               ],
               [
                  -8.398299311638212,
                  43.372460265772617
               ],
               [
                  -8.397711841148018,
                  43.37250004806608
               ],
               [
                  -8.397649172527188,
                  43.37200096115135
               ],
               [
                  -8.397621473337171,
                  43.371946075794575
               ],
               [
                  -8.397586568132928,
                  43.371988383082083
               ],
               [
                  -8.397494599383235,
                  43.372099761391667
               ],
               [
                  -8.397484499930147,
                  43.372115520753404
               ],
               [
                  -8.397447261970562,
                  43.372173350261797
               ],
               [
                  -8.397263069761737,
                  43.372458884096652
               ],
               [
                  -8.397177576403676,
                  43.372521469566259
               ],
               [
                  -8.397114504931142,
                  43.372457913826103
               ],
               [
                  -8.397069247782266,
                  43.372412488020515
               ],
               [
                  -8.396795821528132,
                  43.372316231890508
               ],
               [
                  -8.396718197673399,
                  43.372303017449632
               ],
               [
                  -8.396586445967332,
                  43.372280527589858
               ],
               [
                  -8.39632801947821,
                  43.372228121555693
               ],
               [
                  -8.39591389125016,
                  43.372132843172352
               ],
               [
                  -8.395949120523206,
                  43.372086186476722
               ],
               [
                  -8.395967361337188,
                  43.372066777779104
               ],
               [
                  -8.396146359505234,
                  43.371876260262923
               ],
               [
                  -8.396180149584987,
                  43.371845826133885
               ],
               [
                  -8.39620539263546,
                  43.37182280111378
               ],
               [
                  -8.396308522087519,
                  43.371766979665686
               ],
               [
                  -8.396429206746088,
                  43.371732946370486
               ],
               [
                  -8.396538196261048,
                  43.371722903778334
               ],
               [
                  -8.396723774949443,
                  43.371741369847527
               ],
               [
                  -8.396749683831747,
                  43.371743942588871
               ],
               [
                  -8.396786537090801,
                  43.371707646881489
               ],
               [
                  -8.396832946737701,
                  43.371584962535778
               ],
               [
                  -8.396837911125722,
                  43.37148308592316
               ],
               [
                  -8.396726489241535,
                  43.371468339206082
               ],
               [
                  -8.396526438117551,
                  43.371441983417419
               ],
               [
                  -8.39648381425055,
                  43.37142025719254
               ],
               [
                  -8.396446360656533,
                  43.371382499929467
               ],
               [
                  -8.396411912120916,
                  43.371325039459641
               ],
               [
                  -8.396431242317965,
                  43.371180351589665
               ],
               [
                  -8.396499424204787,
                  43.37118601458625
               ],
               [
                  -8.396559500872893,
                  43.371191133898513
               ],
               [
                  -8.396588234908082,
                  43.371193423537513
               ],
               [
                  -8.396620572597739,
                  43.371196133168027
               ],
               [
                  -8.396729084946914,
                  43.371205158131488
               ],
               [
                  -8.39680753090741,
                  43.371211675603028
               ],
               [
                  -8.396821077800993,
                  43.371212825898752
               ],
               [
                  -8.397005011261211,
                  43.371228142076312
               ],
               [
                  -8.397275867469729,
                  43.371229720329318
               ],
               [
                  -8.397734358829545,
                  43.371236813408089
               ],
               [
                  -8.397666289301545,
                  43.370921297562205
               ],
               [
                  -8.398310405924802,
                  43.370862462408361
               ],
               [
                  -8.398618284241131,
                  43.370844382911358
               ],
               [
                  -8.398709003381041,
                  43.370833506312451
               ],
               [
                  -8.399059708531905,
                  43.370791233549411
               ],
               [
                  -8.399025180285285,
                  43.370852531662216
               ],
               [
                  -8.399028867937872,
                  43.371180885854137
               ],
               [
                  -8.399006166483716,
                  43.371227053856643
               ],
               [
                  -8.399020241663992,
                  43.371364812234674
               ],
               [
                  -8.39907809266268,
                  43.371419115823635
               ],
               [
                  -8.39922756307319,
                  43.371683134829524
               ],
               [
                  -8.399258677845971,
                  43.371757267796944
               ]
            ]
         }
      }
}